flux_limiter-0.1.19.dist-info/WHEEL
flux_limiter-0.1.19.dist-info/METADATA
flux_limiter-0.1.19.dist-info/RECORD
flux_limiter-0.1.19.dist-info/licenses/LICENSE
lib/libhiredis.a
lib/pkgconfig/hiredis.pc
lib/cmake/hiredis/hiredis-config.cmake
lib/cmake/hiredis/hiredis-config-version.cmake
lib/cmake/hiredis/hiredis-targets-release.cmake
lib/cmake/hiredis/hiredis-targets.cmake
build/native/hiredis.targets
flux/limiter.py
flux/analytics.py
flux/cli.py
flux/stats.py
flux/worker.py
flux/identity.py
flux/monitor.py
flux/exceptions.py
flux/py.typed
flux/_flux_core.cpython-311-i386-linux-gnu.so
flux/__main__.py
flux/decorators.py
flux/config.py
flux/__init__.py
flux/lua/token_bucket.lua
flux/lua/leaky_bucket.lua
flux/lua/gcra.lua
flux/lua/fcfs.lua
include/hiredis/read.h
include/hiredis/async.h
include/hiredis/alloc.h
include/hiredis/sockcompat.h
include/hiredis/sds.h
include/hiredis/hiredis.h
include/hiredis/adapters/macosx.h
include/hiredis/adapters/ae.h
include/hiredis/adapters/libevent.h
include/hiredis/adapters/libhv.h
include/hiredis/adapters/libsdevent.h
include/hiredis/adapters/poll.h
include/hiredis/adapters/libev.h
include/hiredis/adapters/libuv.h
include/hiredis/adapters/ivykis.h
include/hiredis/adapters/glib.h
include/hiredis/adapters/qt.h
include/hiredis/adapters/redismoduleapi.h
