Metadata-Version: 2.2
Name: flux-limiter
Version: 0.1.19
Summary: High-performance Python rate limiter for Django, FastAPI, and Flask using Redis and Lua
Keywords: rate limiting,python rate limiter,redis rate limiter,api rate limiting,throttling,django rate limit,fastapi rate limiter,flask rate limiter,gcra,distributed systems
Author: Swayam Jain
License: MIT
Classifier: Programming Language :: Python :: 3
Classifier: Programming Language :: Python :: 3 :: Only
Classifier: License :: OSI Approved :: MIT License
Classifier: Framework :: Django
Classifier: Framework :: FastAPI
Classifier: Framework :: Flask
Classifier: Topic :: Internet :: WWW/HTTP
Classifier: Topic :: Software Development :: Libraries
Classifier: Topic :: System :: Distributed Computing
Classifier: Intended Audience :: Developers
Project-URL: Homepage, https://github.com/Swam244/flux
Project-URL: Repository, https://github.com/Swam244/flux
Project-URL: Issues, https://github.com/Swam244/flux/issues
Project-URL: Documentation, https://github.com/Swam244/flux#readme
Requires-Python: >=3.11
Requires-Dist: redis>=7.1.0
Requires-Dist: tomli>=2.3.0
Provides-Extra: test
Requires-Dist: uvicorn>=0.40.0; extra == "test"
Requires-Dist: gunicorn>=23.0.0; extra == "test"
Requires-Dist: flask>=3.1.2; extra == "test"
Requires-Dist: django>=5.2.9; extra == "test"
Requires-Dist: fastapi>=0.128.0; extra == "test"
Requires-Dist: httpx>=0.28.1; extra == "test"
Requires-Dist: pytest>=9.0.2; extra == "test"
Requires-Dist: pytest-django>=4.5.0; extra == "test"
Provides-Extra: dev
Requires-Dist: pytest>=9.0.2; extra == "dev"
